honkairail/__init__.py
honkairail/src/__init__.py
honkairail/src/tools/__init__.py
honkairail/src/tools/api.py
honkairail/src/tools/modalV1.py
honkairail/src/tools/modalV2.py
honkairail/src/tools/translate.py
honkairail/src/tools/utilities.py
honkairail/starrailapi.py
honkairail-1.1.4.dist-info/METADATA
honkairail-1.1.4.dist-info/WHEEL
honkairail-1.1.4.dist-info/RECORD
