Metadata-Version: 2.1
Name: honkairail
Version: 1.1.4
Summary: A simple and convenient model for Mihoyo API which is complemented by other resources
Home-page: https://github.com/DEViantUA/HonkaiRail
Author: None
Requires-Python: >=3.9,<4.0
Classifier: Programming Language :: Python :: 3
Classifier: Programming Language :: Python :: 3.9
Classifier: Programming Language :: Python :: 3.10
Classifier: Programming Language :: Python :: 3.11
Project-URL: Repository, https://github.com/DEViantUA/HonkaiRail
